{
  "cells": {
    "10": {
      "stdout": "03:02:44 - INFO - LOGGING (log: True)\n03:02:44 - INFO - BLOCKS (total: 5, dynamic: 2, static: 3, eventful: 0)\n03:02:44 - INFO - GRAPH (nodes: 5, edges: 6, alg. depth: 3, loop depth: 0, runtime: 0.071ms)\n",
      "stderr": null,
      "figures": []
    },
    "12": {
      "stdout": "03:02:44 - INFO - STARTING -> TRANSIENT (Duration: 15.00s)\n03:02:44 - INFO - --------------------   1% | 0.0s<0.2s | 1133.3 it/s\n03:02:44 - INFO - ####----------------  20% | 0.0s<0.1s | 2115.2 it/s\n03:02:44 - INFO - ########------------  40% | 0.0s<0.0s | 2146.1 it/s\n03:02:44 - INFO - ############--------  60% | 0.1s<0.0s | 2125.2 it/s\n03:02:44 - INFO - ################----  80% | 0.1s<0.0s | 2155.4 it/s\n03:02:44 - INFO - #################### 100% | 0.1s<--:-- | 2135.4 it/s\n03:02:44 - INFO - FINISHED -> TRANSIENT (total steps: 207, successful: 174, runtime: 114.48 ms)\n",
      "stderr": null,
      "figures": [
        "pendulum_0.svg"
      ]
    },
    "14": {
      "stdout": null,
      "stderr": null,
      "figures": [
        "pendulum_1.svg"
      ]
    }
  },
  "executedAt": "2026-05-20T03:02:46.339968+00:00",
  "duration": 6378,
  "success": true
}