{
  "cells": {
    "9": {
      "stdout": "14:54:08 - INFO - LOGGING (log: True)\n14:54:08 - INFO - BLOCKS (total: 9, dynamic: 3, static: 6, eventful: 0)\n14:54:08 - INFO - GRAPH (nodes: 9, edges: 14, alg. depth: 5, loop depth: 0, runtime: 0.128ms)\n",
      "stderr": null,
      "figures": []
    },
    "11": {
      "stdout": "14:54:09 - INFO - STARTING -> TRANSIENT (Duration: 100.00s)\n14:54:09 - INFO - --------------------   1% | 0.0s<2.1s | 730.7 it/s\n14:54:09 - INFO - ####----------------  20% | 0.5s<01:49:14 | 709.7 it/s\n14:54:10 - INFO - ########------------  40% | 1.0s<0.9s | 756.0 it/s\n14:54:10 - INFO - ############--------  60% | 1.5s<55:07 | 754.3 it/s\n14:54:10 - INFO - ################----  80% | 1.9s<0.5s | 713.6 it/s\n14:54:11 - INFO - #################### 100% | 2.3s<--:-- | 732.9 it/s\n14:54:11 - INFO - FINISHED -> TRANSIENT (total steps: 1677, successful: 1228, runtime: 2337.15 ms)\n",
      "stderr": null,
      "figures": []
    }
  },
  "executedAt": "2026-05-17T14:54:12.356920+00:00",
  "duration": 8067,
  "success": true
}