{
  "cells": {
    "17": {
      "stdout": "07:46:01 - INFO - LOGGING (log: True)\n07:46:01 - INFO - BLOCKS (total: 2, dynamic: 1, static: 1, eventful: 0)\n07:46:01 - INFO - GRAPH (nodes: 2, edges: 1, alg. depth: 1, loop depth: 0, runtime: 0.028ms)\n07:46:01 - INFO - STARTING -> TRANSIENT (Duration: 2000.00s)\n07:46:01 - INFO - --------------------   1% | 0.7s<19.7s | 26.2 it/s\n07:46:02 - INFO - #####---------------  27% | 1.0s<1.0s | 25.6 it/s\n07:46:03 - INFO - ########------------  40% | 1.9s<12.8s | 14.4 it/s\n07:46:06 - INFO - ########------------  41% | 4.8s<20.5s | 31.1 it/s\n07:46:06 - INFO - #############-------  67% | 5.4s<1.0s | 15.3 it/s\n07:46:07 - INFO - ################----  80% | 6.3s<3.6s | 15.0 it/s\n07:46:10 - INFO - ################----  81% | 9.0s<8.3s | 36.1 it/s\n07:46:10 - INFO - #################### 100% | 9.4s<--:-- | 15.8 it/s\n07:46:10 - INFO - FINISHED -> TRANSIENT (total steps: 341, successful: 234, runtime: 9444.73 ms)\n",
      "stderr": null,
      "figures": []
    },
    "19": {
      "stdout": null,
      "stderr": null,
      "figures": [
        "nested_subsystems_0.svg"
      ]
    }
  },
  "executedAt": "2026-06-12T07:46:12.103193+00:00",
  "duration": 15978,
  "success": true
}