{
  "cells": {
    "14": {
      "stdout": "00:54:53 - INFO - LOGGING (log: True)\n00:54:53 - INFO - BLOCKS (total: 6, dynamic: 2, static: 4, eventful: 0)\n00:54:53 - INFO - GRAPH (nodes: 6, edges: 8, alg. depth: 4, loop depth: 0, runtime: 0.155ms)\n00:54:53 - INFO - STARTING -> TRANSIENT (Duration: 100.00s)\n00:54:53 - INFO - --------------------   1% | 0.0s<0.2s | 917.8 it/s\n00:54:53 - INFO - ####----------------  20% | 0.1s<179:12:24 | 1816.2 it/s\n00:54:53 - INFO - ########------------  40% | 0.1s<0.1s | 1879.8 it/s\n00:54:53 - INFO - ############--------  60% | 0.2s<48:04:41 | 1660.5 it/s\n00:54:53 - INFO - ################----  80% | 0.3s<0.0s | 1686.3 it/s\n00:54:53 - INFO - #################### 100% | 0.3s<--:-- | 1713.8 it/s\n00:54:53 - INFO - FINISHED -> TRANSIENT (total steps: 455, successful: 291, runtime: 293.30 ms)\n",
      "stderr": null,
      "figures": []
    },
    "16": {
      "stdout": null,
      "stderr": null,
      "figures": [
        "pid_controller_0.svg"
      ]
    }
  },
  "executedAt": "2026-06-26T00:54:54.971272+00:00",
  "duration": 6343,
  "success": true
}