{
  "cells": {
    "14": {
      "stdout": "09:07:22 - INFO - LOGGING (log: True)\n09:07:22 - INFO - BLOCKS (total: 6, dynamic: 2, static: 4, eventful: 0)\n09:07:22 - INFO - GRAPH (nodes: 6, edges: 8, alg. depth: 4, loop depth: 0, runtime: 0.169ms)\n09:07:22 - INFO - STARTING -> TRANSIENT (Duration: 100.00s)\n09:07:22 - INFO - --------------------   1% | 0.0s<0.2s | 965.8 it/s\n09:07:22 - INFO - ####----------------  20% | 0.1s<185:58:31 | 1428.4 it/s\n09:07:22 - INFO - ########------------  40% | 0.2s<0.1s | 2417.0 it/s\n09:07:22 - INFO - ############--------  60% | 0.2s<41:50:08 | 1902.4 it/s\n09:07:22 - INFO - ################----  80% | 0.3s<0.0s | 1656.1 it/s\n09:07:22 - INFO - #################### 100% | 0.3s<--:-- | 1918.7 it/s\n09:07:22 - INFO - FINISHED -> TRANSIENT (total steps: 455, successful: 291, runtime: 319.72 ms)\n",
      "stderr": null,
      "figures": []
    },
    "16": {
      "stdout": null,
      "stderr": null,
      "figures": [
        "pid_controller_0.svg"
      ]
    }
  },
  "executedAt": "2026-05-20T09:07:24.095975+00:00",
  "duration": 6550,
  "success": true
}