{
  "cells": {
    "9": {
      "stdout": "14:02:59 - INFO - LOGGING (log: True)\n14:02:59 - INFO - BLOCKS (total: 4, dynamic: 2, static: 2, eventful: 0)\n14:02:59 - INFO - GRAPH (nodes: 4, edges: 5, alg. depth: 1, loop depth: 0, runtime: 0.067ms)\n",
      "stderr": null,
      "figures": []
    },
    "11": {
      "stdout": "14:02:59 - INFO - STARTING -> TRANSIENT (Duration: 3.00s)\n14:02:59 - INFO - --------------------   3% | 0.0s<0.1s | 385.7 it/s\n14:02:59 - INFO - ####----------------  20% | 0.2s<0.4s | 914.8 it/s\n14:02:59 - INFO - ########------------  40% | 0.2s<0.1s | 798.3 it/s\n14:02:59 - INFO - ############--------  60% | 0.3s<0.1s | 816.5 it/s\n14:02:59 - INFO - ################----  80% | 0.3s<0.0s | 810.5 it/s\n14:02:59 - INFO - #################### 100% | 0.3s<--:-- | 807.5 it/s\n14:02:59 - INFO - FINISHED -> TRANSIENT (total steps: 204, successful: 174, runtime: 309.45 ms)\n",
      "stderr": null,
      "figures": [
        "spectrum_analysis_0.svg",
        "spectrum_analysis_1.svg"
      ]
    },
    "17": {
      "stdout": null,
      "stderr": null,
      "figures": [
        "spectrum_analysis_2.svg"
      ]
    }
  },
  "executedAt": "2026-07-03T14:03:01.306883+00:00",
  "duration": 6353,
  "success": true
}