{
  "cells": {
    "17": {
      "stdout": "00:49:40 - INFO - LOGGING (log: True)\n00:49:40 - INFO - BLOCKS (total: 5, dynamic: 2, static: 3, eventful: 1)\n00:49:40 - INFO - GRAPH (nodes: 5, edges: 9, alg. depth: 2, loop depth: 0, runtime: 0.064ms)\n",
      "stderr": null,
      "figures": []
    },
    "18": {
      "stdout": "00:49:40 - INFO - STARTING -> TRANSIENT (Duration: 10.00s)\n00:49:40 - INFO - --------------------   1% | 0.0s<0.9s | 2147.0 it/s\n00:49:40 - INFO - ####----------------  20% | 0.2s<0.7s | 2194.9 it/s\n00:49:41 - INFO - ########------------  40% | 0.4s<0.6s | 2059.5 it/s\n00:49:41 - INFO - ############--------  60% | 0.6s<0.2s | 4164.0 it/s\n00:49:41 - INFO - ################----  80% | 0.7s<0.1s | 3841.5 it/s\n00:49:41 - INFO - #################### 100% | 0.8s<--:-- | 3515.6 it/s\n00:49:41 - INFO - FINISHED -> TRANSIENT (total steps: 2130, successful: 2083, runtime: 812.84 ms)\n",
      "stderr": null,
      "figures": []
    },
    "20": {
      "stdout": null,
      "stderr": null,
      "figures": [
        "elastic_pendulum_0.svg"
      ]
    },
    "22": {
      "stdout": null,
      "stderr": null,
      "figures": [
        "elastic_pendulum_1.svg"
      ]
    }
  },
  "executedAt": "2026-06-07T00:49:42.958155+00:00",
  "duration": 6928,
  "success": true
}