{
  "cells": {
    "14": {
      "stdout": "19:51:22 - INFO - LOGGING (log: True)\n19:51:22 - INFO - BLOCKS (total: 6, dynamic: 2, static: 4, eventful: 0)\n19:51:22 - INFO - GRAPH (nodes: 6, edges: 8, alg. depth: 4, loop depth: 0, runtime: 0.122ms)\n19:51:22 - INFO - STARTING -> TRANSIENT (Duration: 100.00s)\n19:51:22 - INFO - --------------------   1% | 0.0s<0.3s | 762.8 it/s\n19:51:22 - INFO - ####----------------  20% | 0.1s<125:07:51 | 2639.6 it/s\n19:51:22 - INFO - ########------------  40% | 0.1s<0.1s | 1744.6 it/s\n19:51:22 - INFO - ############--------  60% | 0.2s<41:48:58 | 1764.2 it/s\n19:51:22 - INFO - ################----  80% | 0.3s<0.0s | 1854.8 it/s\n19:51:22 - INFO - #################### 100% | 0.3s<--:-- | 1873.3 it/s\n19:51:22 - INFO - FINISHED -> TRANSIENT (total steps: 455, successful: 291, runtime: 291.56 ms)\n",
      "stderr": null,
      "figures": []
    },
    "16": {
      "stdout": null,
      "stderr": null,
      "figures": [
        "pid_controller_0.svg"
      ]
    }
  },
  "executedAt": "2026-07-02T19:51:24.073357+00:00",
  "duration": 6228,
  "success": true
}