{
  "cells": {
    "17": {
      "stdout": "08:57:29 - INFO - LOGGING (log: True)\n08:57:29 - INFO - BLOCKS (total: 2, dynamic: 1, static: 1, eventful: 0)\n08:57:29 - INFO - GRAPH (nodes: 2, edges: 1, alg. depth: 1, loop depth: 0, runtime: 0.034ms)\n",
      "stderr": null,
      "figures": []
    },
    "19": {
      "stdout": "08:57:29 - INFO - STARTING -> TRANSIENT (Duration: 100.00s)\n08:57:29 - INFO - --------------------   1% | 0.0s<0.7s | 5045.0 it/s\n08:57:29 - INFO - ####----------------  20% | 0.3s<0.6s | 3879.3 it/s\n08:57:30 - INFO - ########------------  40% | 0.7s<0.6s | 3559.6 it/s\n08:57:30 - INFO - ############--------  60% | 1.0s<1.6s | 4262.0 it/s\n08:57:30 - INFO - ################----  80% | 1.3s<0.2s | 4501.7 it/s\n08:57:31 - INFO - #################### 100% | 1.7s<--:-- | 3981.5 it/s\n08:57:31 - INFO - FINISHED -> TRANSIENT (total steps: 6610, successful: 4889, runtime: 1685.83 ms)\n",
      "stderr": null,
      "figures": []
    },
    "21": {
      "stdout": null,
      "stderr": null,
      "figures": [
        "poincare_maps_0.svg"
      ]
    }
  },
  "executedAt": "2026-07-02T08:57:32.950136+00:00",
  "duration": 7788,
  "success": true
}