{
  "cells": {
    "20": {
      "stdout": "18:33:32 - INFO - LOGGING (log: True)\n18:33:32 - INFO - BLOCKS (total: 11, dynamic: 2, static: 9, eventful: 0)\n18:33:32 - INFO - GRAPH (nodes: 11, edges: 17, alg. depth: 5, loop depth: 0, runtime: 0.088ms)\n18:33:32 - INFO - STARTING -> TRANSIENT (Duration: 100.00s)\n18:33:32 - INFO - --------------------   1% | 0.0s<0.3s | 3354.7 it/s\n18:33:32 - INFO - ####----------------  20% | 0.1s<0.2s | 4807.9 it/s\n18:33:32 - INFO - ########------------  40% | 0.2s<0.3s | 2784.4 it/s\n18:33:32 - INFO - ############--------  60% | 0.4s<0.2s | 2810.4 it/s\n18:33:33 - INFO - ###############-----  75% | 1.4s<01:04:14 | 5220.0 it/s\n18:33:33 - INFO - ################----  80% | 1.5s<0.0s | 6470.3 it/s\n18:33:34 - INFO - #################### 100% | 1.6s<--:-- | 2470.1 it/s\n18:33:34 - INFO - FINISHED -> TRANSIENT (total steps: 5055, successful: 2409, runtime: 1604.71 ms)\n",
      "stderr": null,
      "figures": []
    },
    "22": {
      "stdout": null,
      "stderr": null,
      "figures": [
        "stick_slip_0.svg"
      ]
    },
    "24": {
      "stdout": null,
      "stderr": null,
      "figures": [
        "stick_slip_1.svg"
      ]
    }
  },
  "executedAt": "2026-06-07T18:33:38.103163+00:00",
  "duration": 9376,
  "success": true
}