{
  "cells": {
    "20": {
      "stdout": "00:55:55 - INFO - LOGGING (log: True)\n00:55:55 - INFO - BLOCKS (total: 17, dynamic: 3, static: 14, eventful: 2)\n00:55:55 - INFO - GRAPH (nodes: 17, edges: 22, alg. depth: 6, loop depth: 0, runtime: 0.189ms)\n00:55:55 - INFO - STARTING -> TRANSIENT (Duration: 30.00s)\n00:55:56 - INFO - --------------------   1% | 0.2s<7.9s | 758.8 it/s\n00:55:57 - INFO - ###-----------------  15% | 1.2s<6.1s | 775.8 it/s\n00:55:57 - INFO - ####----------------  20% | 1.5s<7.2s | 780.7 it/s\n00:55:58 - INFO - ######--------------  34% | 2.5s<4.6s | 832.6 it/s\n00:55:58 - INFO - ########------------  40% | 2.9s<5.0s | 761.5 it/s\n00:55:59 - INFO - ###########---------  55% | 3.9s<3.6s | 754.7 it/s\n00:56:00 - INFO - ############--------  60% | 4.2s<2.0s | 952.4 it/s\n00:56:01 - INFO - ###############-----  75% | 5.2s<1.3s | 915.4 it/s\n00:56:01 - INFO - ################----  80% | 5.5s<1.4s | 740.3 it/s\n00:56:02 - INFO - ##################--  93% | 6.5s<0.4s | 806.8 it/s\n00:56:02 - INFO - #################### 100% | 6.9s<--:-- | 691.2 it/s\n00:56:02 - INFO - FINISHED -> TRANSIENT (total steps: 5837, successful: 4938, runtime: 6915.08 ms)\n",
      "stderr": null,
      "figures": []
    },
    "22": {
      "stdout": null,
      "stderr": null,
      "figures": [
        "dcmotor_control_0.svg",
        "dcmotor_control_1.svg"
      ]
    }
  },
  "executedAt": "2026-06-02T00:56:06.359961+00:00",
  "duration": 15084,
  "success": true
}