{
  "cells": {
    "11": {
      "stdout": "18:37:46 - INFO - LOGGING (log: True)\n18:37:46 - INFO - BLOCKS (total: 5, dynamic: 1, static: 4, eventful: 0)\n18:37:46 - INFO - GRAPH (nodes: 5, edges: 6, alg. depth: 3, loop depth: 0, runtime: 0.084ms)\n18:37:46 - INFO - STARTING -> TRANSIENT (Duration: 12.00s)\n18:37:46 - INFO - --------------------   1% | 0.0s<0.1s | 9214.0 it/s\n18:37:46 - INFO - ####----------------  20% | 0.0s<0.1s | 9077.6 it/s\n18:37:46 - INFO - ########------------  40% | 0.1s<0.1s | 10757.6 it/s\n18:37:46 - INFO - ############--------  60% | 0.1s<0.0s | 10422.6 it/s\n18:37:46 - INFO - ################----  80% | 0.1s<0.0s | 10512.8 it/s\n18:37:46 - INFO - #################### 100% | 0.1s<--:-- | 10198.8 it/s\n18:37:46 - INFO - FINISHED -> TRANSIENT (total steps: 1201, successful: 1201, runtime: 134.53 ms)\n",
      "stderr": null,
      "figures": []
    },
    "15": {
      "stdout": null,
      "stderr": null,
      "figures": [
        "linear_feedback_0.svg"
      ]
    }
  },
  "executedAt": "2026-06-06T18:37:50.751080+00:00",
  "duration": 8898,
  "success": true
}