{
  "cells": {
    "20": {
      "stdout": "09:11:37 - INFO - LOGGING (log: True)\n09:11:37 - INFO - BLOCKS (total: 11, dynamic: 2, static: 9, eventful: 0)\n09:11:37 - INFO - GRAPH (nodes: 11, edges: 17, alg. depth: 5, loop depth: 0, runtime: 0.116ms)\n09:11:37 - INFO - STARTING -> TRANSIENT (Duration: 100.00s)\n09:11:37 - INFO - --------------------   1% | 0.0s<0.2s | 5069.4 it/s\n09:11:37 - INFO - ####----------------  20% | 0.1s<0.4s | 2135.1 it/s\n09:11:37 - INFO - ########------------  40% | 0.4s<0.4s | 1865.8 it/s\n09:11:38 - INFO - ############--------  60% | 0.6s<0.3s | 1790.3 it/s\n09:11:39 - INFO - ###############-----  75% | 1.6s<02:01:13 | 2120.8 it/s\n09:11:39 - INFO - ################----  80% | 2.3s<0.1s | 2437.3 it/s\n09:11:40 - INFO - #################### 100% | 2.5s<--:-- | 2045.6 it/s\n09:11:40 - INFO - FINISHED -> TRANSIENT (total steps: 5055, successful: 2409, runtime: 2478.57 ms)\n",
      "stderr": null,
      "figures": []
    },
    "22": {
      "stdout": null,
      "stderr": null,
      "figures": [
        "stick_slip_0.svg"
      ]
    },
    "24": {
      "stdout": null,
      "stderr": null,
      "figures": [
        "stick_slip_1.svg"
      ]
    }
  },
  "executedAt": "2026-07-13T09:11:41.564387+00:00",
  "duration": 8385,
  "success": true
}