{
  "cells": {
    "17": {
      "stdout": "00:48:39 - INFO - LOGGING (log: True)\n00:48:39 - INFO - BLOCKS (total: 5, dynamic: 2, static: 3, eventful: 1)\n00:48:39 - INFO - GRAPH (nodes: 5, edges: 9, alg. depth: 2, loop depth: 0, runtime: 0.072ms)\n",
      "stderr": null,
      "figures": []
    },
    "18": {
      "stdout": "00:48:39 - INFO - STARTING -> TRANSIENT (Duration: 10.00s)\n00:48:39 - INFO - --------------------   1% | 0.0s<0.9s | 2140.1 it/s\n00:48:40 - INFO - ####----------------  20% | 0.2s<0.5s | 3277.9 it/s\n00:48:40 - INFO - ########------------  40% | 0.3s<0.5s | 2557.1 it/s\n00:48:40 - INFO - ############--------  60% | 0.5s<0.3s | 2454.6 it/s\n00:48:40 - INFO - ################----  80% | 0.6s<0.2s | 2555.6 it/s\n00:48:40 - INFO - #################### 100% | 0.8s<--:-- | 2454.1 it/s\n00:48:40 - INFO - FINISHED -> TRANSIENT (total steps: 2130, successful: 2083, runtime: 806.52 ms)\n",
      "stderr": null,
      "figures": []
    },
    "20": {
      "stdout": null,
      "stderr": null,
      "figures": [
        "elastic_pendulum_0.svg"
      ]
    },
    "22": {
      "stdout": null,
      "stderr": null,
      "figures": [
        "elastic_pendulum_1.svg"
      ]
    }
  },
  "executedAt": "2026-06-01T00:48:42.206365+00:00",
  "duration": 7095,
  "success": true
}