{
  "cells": {
    "12": {
      "stdout": "00:47:54 - INFO - LOGGING (log: True)\n00:47:54 - INFO - BLOCKS (total: 7, dynamic: 2, static: 5, eventful: 0)\n00:47:54 - INFO - GRAPH (nodes: 7, edges: 9, alg. depth: 4, loop depth: 0, runtime: 0.064ms)\n",
      "stderr": null,
      "figures": []
    },
    "14": {
      "stdout": "00:47:54 - INFO - STARTING -> TRANSIENT (Duration: 25.00s)\n00:47:54 - INFO - --------------------   1% | 0.0s<0.2s | 11874.2 it/s\n00:47:54 - INFO - ####----------------  20% | 0.0s<0.2s | 11674.9 it/s\n00:47:55 - INFO - ########------------  40% | 0.1s<0.1s | 11851.4 it/s\n00:47:55 - INFO - ############--------  60% | 0.1s<0.1s | 11657.6 it/s\n00:47:55 - INFO - ################----  80% | 0.2s<0.1s | 7172.2 it/s\n00:47:55 - INFO - #################### 100% | 0.3s<--:-- | 6024.3 it/s\n00:47:55 - INFO - FINISHED -> TRANSIENT (total steps: 2500, successful: 2500, runtime: 317.44 ms)\n",
      "stderr": null,
      "figures": []
    },
    "16": {
      "stdout": null,
      "stderr": null,
      "figures": [
        "harmonic_oscillator_0.svg"
      ]
    }
  },
  "executedAt": "2026-06-07T00:47:56.383207+00:00",
  "duration": 6176,
  "success": true
}