{
  "cells": {
    "14": {
      "stdout": "03:04:14 - INFO - LOGGING (log: True)\n03:04:14 - INFO - BLOCKS (total: 4, dynamic: 0, static: 4, eventful: 0)\n03:04:14 - INFO - GRAPH (nodes: 4, edges: 6, alg. depth: 1, loop depth: 2, runtime: 0.187ms)\n03:04:14 - INFO - STARTING -> TRANSIENT (Duration: 5.00s)\n03:04:14 - INFO - --------------------   2% | 0.0s<0.1s | 328.7 it/s\n03:04:14 - INFO - ####----------------  21% | 0.0s<0.0s | 3228.3 it/s\n03:04:14 - INFO - ########------------  40% | 0.0s<0.0s | 4738.9 it/s\n03:04:14 - INFO - ############--------  60% | 0.0s<0.0s | 4870.8 it/s\n03:04:14 - INFO - ################----  80% | 0.0s<0.0s | 4947.0 it/s\n03:04:14 - INFO - #################### 100% | 0.0s<--:-- | 4995.6 it/s\n03:04:14 - INFO - FINISHED -> TRANSIENT (total steps: 51, successful: 51, runtime: 33.81 ms)\n",
      "stderr": null,
      "figures": []
    },
    "16": {
      "stdout": null,
      "stderr": null,
      "figures": [
        "algebraic_loop_0.svg"
      ]
    },
    "18": {
      "stdout": "Maximum error: 2.22e-16\n",
      "stderr": null,
      "figures": [
        "algebraic_loop_1.svg"
      ]
    }
  },
  "executedAt": "2026-05-22T03:04:15.556143+00:00",
  "duration": 6615,
  "success": true
}