{
  "cells": {
    "16": {
      "stdout": "07:58:53 - INFO - LOGGING (log: True)\n07:58:53 - INFO - BLOCKS (total: 4, dynamic: 2, static: 2, eventful: 0)\n07:58:53 - INFO - GRAPH (nodes: 4, edges: 3, alg. depth: 1, loop depth: 0, runtime: 0.041ms)\n07:58:53 - INFO - STARTING -> TRANSIENT (Duration: 10.00s)\n07:58:54 - INFO - --------------------   1% | 0.0s<0.1s | 2496.1 it/s\n07:58:54 - INFO - ####----------------  20% | 0.0s<0.0s | 4142.1 it/s\n07:58:54 - INFO - ########------------  40% | 0.1s<0.0s | 4238.2 it/s\n07:58:54 - INFO - ############--------  60% | 0.1s<0.0s | 5603.5 it/s\n07:58:54 - INFO - ################----  80% | 0.1s<0.0s | 3453.9 it/s\n07:58:54 - INFO - #################### 100% | 0.1s<--:-- | 3482.7 it/s\n07:58:54 - INFO - FINISHED -> TRANSIENT (total steps: 415, successful: 363, runtime: 134.40 ms)\n",
      "stderr": null,
      "figures": []
    },
    "20": {
      "stdout": null,
      "stderr": null,
      "figures": [
        "bouncing_ball_0.svg"
      ]
    },
    "22": {
      "stdout": null,
      "stderr": null,
      "figures": [
        "bouncing_ball_1.svg"
      ]
    },
    "24": {
      "stdout": null,
      "stderr": null,
      "figures": [
        "bouncing_ball_2.svg"
      ]
    }
  },
  "executedAt": "2026-06-01T07:58:56.015246+00:00",
  "duration": 6753,
  "success": true
}