{
  "cells": {
    "12": {
      "stdout": "13:43:07 - INFO - LOGGING (log: True)\n13:43:07 - INFO - BLOCKS (total: 7, dynamic: 2, static: 5, eventful: 0)\n13:43:07 - INFO - GRAPH (nodes: 7, edges: 9, alg. depth: 4, loop depth: 0, runtime: 0.089ms)\n",
      "stderr": null,
      "figures": []
    },
    "14": {
      "stdout": "13:43:07 - INFO - STARTING -> TRANSIENT (Duration: 25.00s)\n13:43:07 - INFO - --------------------   1% | 0.0s<0.3s | 7987.3 it/s\n13:43:07 - INFO - ####----------------  20% | 0.1s<0.2s | 8000.5 it/s\n13:43:07 - INFO - ########------------  40% | 0.1s<0.2s | 8537.5 it/s\n13:43:07 - INFO - ############--------  60% | 0.2s<0.1s | 7388.3 it/s\n13:43:07 - INFO - ################----  80% | 0.3s<0.1s | 8106.8 it/s\n13:43:07 - INFO - #################### 100% | 0.3s<--:-- | 8462.7 it/s\n13:43:07 - INFO - FINISHED -> TRANSIENT (total steps: 2500, successful: 2500, runtime: 319.16 ms)\n",
      "stderr": null,
      "figures": []
    },
    "16": {
      "stdout": null,
      "stderr": null,
      "figures": [
        "harmonic_oscillator_0.svg"
      ]
    }
  },
  "executedAt": "2026-06-08T13:43:09.005506+00:00",
  "duration": 6988,
  "success": true
}