{
  "cells": {
    "15": {
      "stdout": "12:58:21 - INFO - LOGGING (log: True)\n12:58:21 - INFO - BLOCKS (total: 8, dynamic: 1, static: 7, eventful: 0)\n12:58:21 - INFO - GRAPH (nodes: 8, edges: 9, alg. depth: 2, loop depth: 0, runtime: 0.082ms)\n12:58:21 - INFO - STARTING -> TRANSIENT (Duration: 20.00s)\n12:58:21 - INFO - --------------------   1% | 0.0s<0.5s | 4192.7 it/s\n12:58:21 - INFO - ####----------------  20% | 0.1s<0.4s | 4563.8 it/s\n12:58:21 - INFO - ########------------  40% | 0.2s<0.2s | 4987.0 it/s\n12:58:21 - INFO - ############--------  60% | 0.3s<0.2s | 5265.6 it/s\n12:58:21 - INFO - ################----  80% | 0.4s<0.1s | 6011.7 it/s\n12:58:21 - INFO - #################### 100% | 0.4s<--:-- | 6070.4 it/s\n12:58:21 - INFO - FINISHED -> TRANSIENT (total steps: 2000, successful: 2000, runtime: 430.91 ms)\n",
      "stderr": null,
      "figures": []
    },
    "17": {
      "stdout": null,
      "stderr": null,
      "figures": [
        "kalman_filter_0.svg"
      ]
    },
    "19": {
      "stdout": null,
      "stderr": null,
      "figures": [
        "kalman_filter_1.svg"
      ]
    }
  },
  "executedAt": "2026-06-14T12:58:23.850474+00:00",
  "duration": 7215,
  "success": true
}