{
  "cells": {
    "14": {
      "stdout": "09:42:37 - INFO - LOGGING (log: True)\n09:42:37 - INFO - BLOCKS (total: 6, dynamic: 2, static: 4, eventful: 0)\n09:42:37 - INFO - GRAPH (nodes: 6, edges: 8, alg. depth: 4, loop depth: 0, runtime: 0.138ms)\n09:42:37 - INFO - STARTING -> TRANSIENT (Duration: 100.00s)\n09:42:37 - INFO - --------------------   1% | 0.0s<0.2s | 1194.5 it/s\n09:42:37 - INFO - ####----------------  20% | 0.1s<166:27:51 | 1951.4 it/s\n09:42:37 - INFO - ########------------  40% | 0.1s<0.1s | 1886.0 it/s\n09:42:37 - INFO - ############--------  60% | 0.2s<52:16:53 | 1524.6 it/s\n09:42:37 - INFO - ################----  80% | 0.3s<0.0s | 2183.3 it/s\n09:42:37 - INFO - #################### 100% | 0.3s<--:-- | 1693.6 it/s\n09:42:37 - INFO - FINISHED -> TRANSIENT (total steps: 455, successful: 291, runtime: 290.31 ms)\n",
      "stderr": null,
      "figures": []
    },
    "16": {
      "stdout": null,
      "stderr": null,
      "figures": [
        "pid_controller_0.svg"
      ]
    }
  },
  "executedAt": "2026-07-10T09:42:38.782870+00:00",
  "duration": 5766,
  "success": true
}