{
  "cells": {
    "9": {
      "stdout": "00:55:19 - INFO - LOGGING (log: True)\n00:55:19 - INFO - BLOCKS (total: 4, dynamic: 2, static: 2, eventful: 0)\n00:55:19 - INFO - GRAPH (nodes: 4, edges: 5, alg. depth: 1, loop depth: 0, runtime: 0.257ms)\n",
      "stderr": null,
      "figures": []
    },
    "11": {
      "stdout": "00:55:19 - INFO - STARTING -> TRANSIENT (Duration: 3.00s)\n00:55:19 - INFO - --------------------   3% | 0.0s<0.1s | 435.0 it/s\n00:55:19 - INFO - ####----------------  20% | 0.1s<0.3s | 1093.1 it/s\n00:55:19 - INFO - ########------------  40% | 0.2s<0.1s | 871.7 it/s\n00:55:19 - INFO - ############--------  60% | 0.2s<0.1s | 871.1 it/s\n00:55:19 - INFO - ################----  80% | 0.2s<0.0s | 862.2 it/s\n00:55:19 - INFO - #################### 100% | 0.2s<--:-- | 865.7 it/s\n00:55:19 - INFO - FINISHED -> TRANSIENT (total steps: 204, successful: 174, runtime: 244.79 ms)\n",
      "stderr": null,
      "figures": [
        "spectrum_analysis_0.svg",
        "spectrum_analysis_1.svg"
      ]
    },
    "17": {
      "stdout": null,
      "stderr": null,
      "figures": [
        "spectrum_analysis_2.svg"
      ]
    }
  },
  "executedAt": "2026-05-25T00:55:21.563843+00:00",
  "duration": 6923,
  "success": true
}