{
  "cells": {
    "22": {
      "stdout": "10:37:24 - INFO - LOGGING (log: True)\n10:37:24 - INFO - BLOCKS (total: 15, dynamic: 2, static: 13, eventful: 0)\n10:37:24 - INFO - GRAPH (nodes: 15, edges: 18, alg. depth: 7, loop depth: 0, runtime: 0.140ms)\n10:37:24 - INFO - STARTING -> TRANSIENT (Duration: 5.00s)\n10:37:25 - INFO - --------------------   1% | 0.2s<5.6s | 876.4 it/s\n10:37:26 - INFO - #-------------------   5% | 1.2s<43.3s | 845.3 it/s\n10:37:27 - INFO - ##------------------  11% | 2.2s<19.1s | 874.4 it/s\n10:37:28 - INFO - ###-----------------  15% | 3.2s<7.3s | 912.8 it/s\n10:37:28 - INFO - ####----------------  20% | 4.0s<4.7s | 920.9 it/s\n10:37:29 - INFO - ####----------------  24% | 5.0s<15.8s | 886.5 it/s\n10:37:30 - INFO - #####---------------  28% | 6.0s<20.3s | 839.0 it/s\n10:37:31 - INFO - ######--------------  32% | 7.0s<7.4s | 844.2 it/s\n10:37:32 - INFO - #######-------------  36% | 8.0s<11.4s | 846.0 it/s\n10:37:33 - INFO - ########------------  40% | 8.8s<3.6s | 931.6 it/s\n10:37:34 - INFO - ########------------  44% | 9.8s<02:07 | 1091.6 it/s\n10:37:35 - INFO - #########-----------  48% | 10.8s<27.3s | 1076.0 it/s\n10:37:36 - INFO - ##########----------  52% | 11.8s<36.8s | 1068.3 it/s\n10:37:37 - INFO - ###########---------  57% | 12.8s<2.4s | 1103.5 it/s\n10:37:38 - INFO - ############--------  60% | 13.4s<2.5s | 1274.5 it/s\n10:37:39 - INFO - ############--------  64% | 14.4s<4.8s | 937.9 it/s\n10:37:40 - INFO - #############-------  69% | 15.4s<4.9s | 1058.1 it/s\n10:37:41 - INFO - ##############------  73% | 16.4s<16.3s | 846.0 it/s\n10:37:42 - INFO - ###############-----  76% | 17.4s<6.0s | 945.9 it/s\n10:37:42 - INFO - ################----  80% | 18.1s<1.5s | 926.7 it/s\n10:37:43 - INFO - ################----  83% | 19.1s<3.5s | 914.9 it/s\n10:37:44 - INFO - #################---  86% | 20.1s<11.5s | 837.8 it/s\n10:37:45 - INFO - #################---  89% | 21.1s<2.7s | 941.5 it/s\n10:37:46 - INFO - ##################--  92% | 22.1s<19.3s | 816.0 it/s\n10:37:47 - INFO - ###################-  96% | 23.1s<4.6s | 1087.9 it/s\n10:37:48 - INFO - #################### 100% | 24.1s<--:-- | 900.7 it/s\n10:37:48 - INFO - FINISHED -> TRANSIENT (total steps: 22942, successful: 15020, runtime: 24087.96 ms)\n",
      "stderr": null,
      "figures": []
    },
    "24": {
      "stdout": "10:37:48 - INFO - LOGGING (log: True)\n10:37:48 - INFO - BLOCKS (total: 15, dynamic: 2, static: 13, eventful: 0)\n10:37:48 - INFO - GRAPH (nodes: 15, edges: 18, alg. depth: 7, loop depth: 0, runtime: 0.118ms)\n10:37:48 - INFO - STARTING -> TRANSIENT (Duration: 5.00s)\n10:37:48 - INFO - --------------------   1% | 0.0s<0.3s | 877.7 it/s\n10:37:48 - INFO - #################### 100% | 0.0s<--:-- | 868.2 it/s\n10:37:48 - INFO - FINISHED -> TRANSIENT (total steps: 9, successful: 9, runtime: 11.51 ms)\n",
      "stderr": null,
      "figures": []
    },
    "26": {
      "stdout": null,
      "stderr": null,
      "figures": [
        "abs_braking_0.svg"
      ]
    }
  },
  "executedAt": "2026-07-16T10:37:51.481179+00:00",
  "duration": 30980,
  "success": true
}