{
  "cells": {
    "13": {
      "stdout": "09:21:29 - INFO - LOGGING (log: True)\n09:21:29 - INFO - BLOCKS (total: 5, dynamic: 2, static: 3, eventful: 0)\n09:21:29 - INFO - GRAPH (nodes: 5, edges: 6, alg. depth: 3, loop depth: 0, runtime: 0.073ms)\n",
      "stderr": null,
      "figures": []
    },
    "15": {
      "stdout": "09:21:29 - INFO - STARTING -> TRANSIENT (Duration: 15.00s)\n09:21:29 - INFO - --------------------   1% | 0.0s<0.2s | 1216.0 it/s\n09:21:29 - INFO - ####----------------  20% | 0.0s<0.1s | 2241.4 it/s\n09:21:29 - INFO - ########------------  40% | 0.1s<0.1s | 2176.6 it/s\n09:21:29 - INFO - ############--------  60% | 0.1s<0.0s | 2338.3 it/s\n09:21:29 - INFO - ################----  80% | 0.1s<0.0s | 2073.7 it/s\n09:21:29 - INFO - #################### 100% | 0.2s<--:-- | 2090.4 it/s\n09:21:29 - INFO - FINISHED -> TRANSIENT (total steps: 327, successful: 254, runtime: 166.74 ms)\n",
      "stderr": null,
      "figures": []
    }
  },
  "executedAt": "2026-05-17T09:21:30.972452+00:00",
  "duration": 5821,
  "success": true
}