{
  "cells": {
    "12": {
      "stdout": "02:56:18 - INFO - LOGGING (log: True)\n02:56:18 - INFO - BLOCKS (total: 7, dynamic: 2, static: 5, eventful: 0)\n02:56:18 - INFO - GRAPH (nodes: 7, edges: 9, alg. depth: 4, loop depth: 0, runtime: 0.090ms)\n",
      "stderr": null,
      "figures": []
    },
    "14": {
      "stdout": "02:56:18 - INFO - STARTING -> TRANSIENT (Duration: 25.00s)\n02:56:18 - INFO - --------------------   1% | 0.0s<0.5s | 4914.9 it/s\n02:56:18 - INFO - ####----------------  20% | 0.1s<0.4s | 5177.5 it/s\n02:56:19 - INFO - ########------------  40% | 0.2s<0.2s | 6451.4 it/s\n02:56:19 - INFO - ############--------  60% | 0.3s<0.2s | 4455.0 it/s\n02:56:19 - INFO - ################----  80% | 0.4s<0.1s | 4343.9 it/s\n02:56:19 - INFO - #################### 100% | 0.6s<--:-- | 4460.4 it/s\n02:56:19 - INFO - FINISHED -> TRANSIENT (total steps: 2500, successful: 2500, runtime: 556.36 ms)\n",
      "stderr": null,
      "figures": []
    },
    "16": {
      "stdout": null,
      "stderr": null,
      "figures": [
        "harmonic_oscillator_0.svg"
      ]
    }
  },
  "executedAt": "2026-07-06T02:56:20.557819+00:00",
  "duration": 6371,
  "success": true
}