{
  "cells": {
    "17": {
      "stdout": "08:29:58 - INFO - LOGGING (log: True)\n08:29:58 - INFO - BLOCKS (total: 2, dynamic: 1, static: 1, eventful: 0)\n08:29:58 - INFO - GRAPH (nodes: 2, edges: 1, alg. depth: 1, loop depth: 0, runtime: 0.023ms)\n08:29:58 - INFO - STARTING -> TRANSIENT (Duration: 2000.00s)\n08:29:58 - INFO - --------------------   1% | 0.4s<7.8s | 47.0 it/s\n08:29:59 - INFO - #####---------------  26% | 0.9s<1.3s | 20.1 it/s\n08:29:59 - INFO - ########------------  40% | 1.6s<9.5s | 28.4 it/s\n08:30:01 - INFO - ########------------  41% | 3.1s<10.0s | 70.2 it/s\n08:30:01 - INFO - ############--------  63% | 3.3s<0.4s | 38.9 it/s\n08:30:02 - INFO - ################----  80% | 4.1s<2.1s | 37.9 it/s\n08:30:03 - INFO - ################----  81% | 5.4s<6.1s | 74.8 it/s\n08:30:04 - INFO - #################### 100% | 5.8s<--:-- | 23.0 it/s\n08:30:04 - INFO - FINISHED -> TRANSIENT (total steps: 368, successful: 249, runtime: 5770.69 ms)\n",
      "stderr": null,
      "figures": []
    },
    "19": {
      "stdout": null,
      "stderr": null,
      "figures": [
        "nested_subsystems_0.svg"
      ]
    }
  },
  "executedAt": "2026-07-24T08:30:05.210677+00:00",
  "duration": 10305,
  "success": true
}