{
  "cells": {
    "11": {
      "stdout": "13:56:15 - INFO - LOGGING (log: True)\n13:56:15 - INFO - BLOCKS (total: 6, dynamic: 0, static: 6, eventful: 0)\n13:56:15 - INFO - GRAPH (nodes: 6, edges: 7, alg. depth: 1, loop depth: 3, runtime: 0.160ms)\n13:56:15 - INFO - STARTING -> TRANSIENT (Duration: 2.00s)\n13:56:15 - INFO - --------------------   1% | 0.0s<1.1s | 187.8 it/s\n13:56:16 - INFO - ####----------------  20% | 0.2s<0.5s | 291.0 it/s\n13:56:16 - INFO - ########------------  40% | 0.2s<0.0s | 10346.5 it/s\n13:56:16 - INFO - ############--------  60% | 0.3s<0.2s | 383.2 it/s\n13:56:16 - INFO - ################----  80% | 0.4s<0.0s | 9697.8 it/s\n13:56:16 - INFO - #################### 100% | 0.4s<--:-- | 9614.7 it/s\n13:56:16 - INFO - FINISHED -> TRANSIENT (total steps: 200, successful: 200, runtime: 379.67 ms)\n",
      "stderr": null,
      "figures": []
    },
    "13": {
      "stdout": null,
      "stderr": null,
      "figures": [
        "diode_circuit_0.svg",
        "diode_circuit_1.svg"
      ]
    },
    "15": {
      "stdout": null,
      "stderr": null,
      "figures": [
        "diode_circuit_2.svg"
      ]
    },
    "17": {
      "stdout": null,
      "stderr": null,
      "figures": [
        "diode_circuit_3.svg"
      ]
    }
  },
  "executedAt": "2026-07-03T13:56:18.133608+00:00",
  "duration": 7165,
  "success": true
}