{
  "cells": {
    "17": {
      "stdout": "07:47:22 - INFO - LOGGING (log: True)\n07:47:22 - INFO - BLOCKS (total: 2, dynamic: 1, static: 1, eventful: 0)\n07:47:22 - INFO - GRAPH (nodes: 2, edges: 1, alg. depth: 1, loop depth: 0, runtime: 0.030ms)\n",
      "stderr": null,
      "figures": []
    },
    "19": {
      "stdout": "07:47:22 - INFO - STARTING -> TRANSIENT (Duration: 100.00s)\n07:47:23 - INFO - --------------------   1% | 0.1s<1.0s | 3433.8 it/s\n07:47:23 - INFO - ####----------------  20% | 0.5s<1.0s | 2324.0 it/s\n07:47:23 - INFO - ########------------  40% | 1.0s<0.7s | 3215.3 it/s\n07:47:24 - INFO - ############--------  60% | 1.4s<1.8s | 3836.1 it/s\n07:47:24 - INFO - ################----  80% | 1.9s<0.3s | 2777.0 it/s\n07:47:25 - INFO - #################### 100% | 2.4s<--:-- | 5671.0 it/s\n07:47:25 - INFO - FINISHED -> TRANSIENT (total steps: 6610, successful: 4889, runtime: 2378.41 ms)\n",
      "stderr": null,
      "figures": []
    },
    "21": {
      "stdout": null,
      "stderr": null,
      "figures": [
        "poincare_maps_0.svg"
      ]
    }
  },
  "executedAt": "2026-06-29T07:47:26.986968+00:00",
  "duration": 8798,
  "success": true
}