{
  "cells": {
    "20": {
      "stdout": "18:30:06 - INFO - LOGGING (log: True)\n18:30:06 - INFO - BLOCKS (total: 11, dynamic: 2, static: 9, eventful: 0)\n18:30:06 - INFO - GRAPH (nodes: 11, edges: 17, alg. depth: 5, loop depth: 0, runtime: 0.100ms)\n18:30:06 - INFO - STARTING -> TRANSIENT (Duration: 100.00s)\n18:30:06 - INFO - --------------------   1% | 0.0s<0.5s | 2181.6 it/s\n18:30:06 - INFO - ####----------------  20% | 0.2s<0.6s | 1360.6 it/s\n18:30:06 - INFO - ########------------  40% | 0.5s<0.4s | 1623.7 it/s\n18:30:07 - INFO - ############--------  60% | 0.7s<0.3s | 1587.6 it/s\n18:30:08 - INFO - ###############-----  75% | 1.7s<02:42:20 | 1265.5 it/s\n18:30:09 - INFO - ###############-----  76% | 2.9s<0.1s | 1900.3 it/s\n18:30:09 - INFO - ################----  80% | 3.0s<0.1s | 1842.5 it/s\n18:30:09 - INFO - #################### 100% | 3.2s<--:-- | 1601.5 it/s\n18:30:09 - INFO - FINISHED -> TRANSIENT (total steps: 5055, successful: 2409, runtime: 3174.84 ms)\n",
      "stderr": null,
      "figures": []
    },
    "22": {
      "stdout": null,
      "stderr": null,
      "figures": [
        "stick_slip_0.svg"
      ]
    },
    "24": {
      "stdout": null,
      "stderr": null,
      "figures": [
        "stick_slip_1.svg"
      ]
    }
  },
  "executedAt": "2026-06-27T18:30:10.966656+00:00",
  "duration": 9684,
  "success": true
}